trilabytepyml/AutoForecast.py
trilabytepyml/AutoRidge.py
trilabytepyml/FeatureSelectorSandbox.py
trilabytepyml/Forecast.py
trilabytepyml/Ridge.py
trilabytepyml/Test.py
trilabytepyml/__init__.py
trilabytepyml/setup.py
trilabytepyml/stats/Statistics.py
trilabytepyml/stats/__init__.py
trilabytepyml/util/Parameters.py
trilabytepyml/util/__init__.py
trilabytepyml-3.7.dist-info/METADATA
trilabytepyml-3.7.dist-info/WHEEL
trilabytepyml-3.7.dist-info/top_level.txt
trilabytepyml-3.7.dist-info/RECORD
