Metadata-Version: 2.1
Name: trilabytepyml
Version: 3.7
Summary: Trilabyte Python Machine Learning
Home-page: http://github.com/smutchler/src
Author: Scott Mutchler
Author-email: smutchler@trilabyte.com
License: GPLv3
Requires-Dist: pmdarima
Requires-Dist: loess
Requires-Dist: scikit-learn >=1.1.2
Requires-Dist: numpy
Requires-Dist: scipy
Requires-Dist: pandas
